fastai_amalgam/__init__.py
fastai_amalgam/_nbdev.py
fastai_amalgam/loss_funcs.py
fastai_amalgam/show_data.py
fastai_amalgam/utils.py
fastai_amalgam/augment/__init__.py
fastai_amalgam/augment/albumentations.py
fastai_amalgam/augment/kornia.py
fastai_amalgam/augment/pil_filters.py
fastai_amalgam/export/__init__.py
fastai_amalgam/export/onnx.py
fastai_amalgam/interpret/__init__.py
fastai_amalgam/interpret/all.py
fastai_amalgam/interpret/compare.py
fastai_amalgam/interpret/gradcam.py
fastai_amalgam/interpret/interpret.py
fastai_amalgam-0.0.26.dist-info/LICENSE
fastai_amalgam-0.0.26.dist-info/METADATA
fastai_amalgam-0.0.26.dist-info/WHEEL
fastai_amalgam-0.0.26.dist-info/entry_points.txt
fastai_amalgam-0.0.26.dist-info/top_level.txt
fastai_amalgam-0.0.26.dist-info/RECORD
