Metadata-Version: 2.1
Name: fastai-amalgam
Version: 0.0.26
Summary: A collection of various CV focused utilities for the fastai library. Includes interpretation, data augmentation, gradcam, loss-functions, model conversion utils, etc
Home-page: https://github.com/Synopsis/fastai_amalgam/tree/master/
Author: Rahul Somani
Author-email: rsomani95@gmail.com
License: Apache Software License 2.0
Keywords: fastai,deep learning,visualisation,interpretation
Platform: UNKNOWN
Classifier: Development Status :: 3 - Alpha
Classifier: Intended Audience :: Developers
Classifier: License :: OSI Approved :: Apache Software License
Classifier: Natural Language :: English
Classifier: Programming Language :: Python :: 3.6
Classifier: Programming Language :: Python :: 3.7
Classifier: Programming Language :: Python :: 3.8
Requires-Python: >=3.6
